slpp.py
SLPP-1.2.3.dist-info/LICENSE
SLPP-1.2.3.dist-info/METADATA
SLPP-1.2.3.dist-info/WHEEL
SLPP-1.2.3.dist-info/top_level.txt
SLPP-1.2.3.dist-info/RECORD
