Metadata-Version: 2.1
Name: SLPP
Version: 1.2.3
Summary: SLPP is a simple lua-python data structures parser
Home-page: https://github.com/SirAnthony/slpp
Author: SirAnthony
License: MIT
Keywords: lua
Platform: UNKNOWN
